{
  "parent": "minecraft:recipes/root",
  "rewards": {
    "recipes": [
      "craftandhunt:bear_brown_upgraded_to_u_bear_brown_leggings"
    ]
  },
  "criteria": {
    "dragon_leggings": {
      "trigger": "minecraft:inventory_changed",
      "conditions": {
        "items": [
          {
            "item": "craftandhunt:dragon_leggings"
          }
        ]
      }
    },
    "has_the_recipe": {
      "trigger": "minecraft:recipe_unlocked",
      "conditions": {
        "recipe": "craftandhunt:bear_brown_upgraded_to_u_bear_brown_leggings"
      }
    }
  },
  "requirements": [
    [
      "dragon_leggings",
      "has_the_recipe"
    ]
  ]
}