{
  "parent": "minecraft:recipes/root",
  "rewards": {
    "recipes": [
      "craftandhunt:stray_upgraded_to_u_stray_boots"
    ]
  },
  "criteria": {
    "dragon_boots": {
      "trigger": "minecraft:inventory_changed",
      "conditions": {
        "items": [
          {
            "item": "craftandhunt:dragon_boots"
          }
        ]
      }
    },
    "has_the_recipe": {
      "trigger": "minecraft:recipe_unlocked",
      "conditions": {
        "recipe": "craftandhunt:stray_upgraded_to_u_stray_boots"
      }
    }
  },
  "requirements": [
    [
      "dragon_boots",
      "has_the_recipe"
    ]
  ]
}